minicli/__init__.py
pyminiCLI-0.3.1.dist-info/LICENSE.txt
pyminiCLI-0.3.1.dist-info/METADATA
pyminiCLI-0.3.1.dist-info/WHEEL
pyminiCLI-0.3.1.dist-info/top_level.txt
pyminiCLI-0.3.1.dist-info/RECORD
