Metadata-Version: 2.1
Name: pyminiCLI
Version: 0.3.1
Summary: quick and easy command-line interfaces
Home-page: https://github.com/HDictus/pyminiCLI
Author: HDIctus
Author-email: h.t.dictus@gmail.com
License: MIT
Platform: UNKNOWN
